CHANGES.txt
DESCRIPTION.rst
LICENSE.txt
MANIFEST.in
README.md
setup.py
bayrell_aio/__init__.py
bayrell_aio/connection.py
bayrell_aio/const.py
bayrell_aio/fs.py
bayrell_aio/http.py
bayrell_aio/streams.py
bayrell_aio.egg-info/PKG-INFO
bayrell_aio.egg-info/SOURCES.txt
bayrell_aio.egg-info/dependency_links.txt
bayrell_aio.egg-info/requires.txt
bayrell_aio.egg-info/top_level.txt
examples/http/client.py
examples/http/proxy.py
examples/http/server.py