Metadata-Version: 1.1
Name: bayrell-aio
Version: 0.2
Summary: Async io library for Bayrell Web Application Server
Home-page: https://github.com/bayrell/bayrell-io
Author: Ildar Bikmamatov
Author-email: vistoyn@gmail.com
License: Лицензия на программу для ЭВМ "Байрель"
Platform: UNKNOWN
Classifier: Development Status :: 1 - Planning
Classifier: Environment :: Console
Classifier: Environment :: Web Environment
Classifier: Intended Audience :: Developers
Classifier: Operating System :: OS Independent
Classifier: Programming Language :: Python
Classifier: Programming Language :: Python :: 3.5
Classifier: Topic :: Internet
Classifier: Topic :: Internet :: Proxy Servers
Classifier: Topic :: Internet :: WWW/HTTP
Classifier: Topic :: Internet :: WWW/HTTP :: Dynamic Content
Classifier: Topic :: Internet :: WWW/HTTP :: HTTP Servers
